{
  "annotations": {
    "list": []
  },
  "editable": true,
  "gnetId": null,
  "graphTooltip": 0,
  "hideControls": false,
  "id": 5,
  "links": [],
  "refresh": "5s",
  "rows": [
    {
      "collapse": false,
      "height": 250,
      "panels": [
        {
          "aliasColors": {},
          "bars": false,
          "dashLength": 10,
          "dashes": false,
          "datasource": null,
          "fill": 1,
          "id": 19,
          "legend": {
            "avg": false,
            "current": false,
            "max": false,
            "min": false,
            "show": true,
            "total": false,
            "values": false
          },
          "lines": true,
          "linewidth": 1,
          "links": [],
          "nullPointMode": "null",
          "percentage": false,
          "pointradius": 5,
          "points": false,
          "renderer": "flot",
          "seriesOverrides": [],
          "spaceLength": 10,
          "span": 4,
          "stack": false,
          "steppedLine": false,
          "targets": [
            {
              "refId": "A",
              "target": "datadealer.datadealer.device-worker.zmq-dequeue.*_rate"
            },
            {
              "refId": "B",
              "target": "datadealer.datadealer.dealer.devsvcworker.zmq-dequeue.*_rate"
            }
          ],
          "thresholds": [],
          "timeFrom": null,
          "timeShift": null,
          "title": "DD device worker dequeuing rates",
          "tooltip": {
            "shared": true,
            "sort": 0,
            "value_type": "individual"
          },
          "type": "graph",
          "xaxis": {
            "buckets": null,
            "mode": "time",
            "name": null,
            "show": true,
            "values": []
          },
          "yaxes": [
            {
              "format": "hertz",
              "label": null,
              "logBase": 1,
              "max": null,
              "min": null,
              "show": true
            },
            {
              "format": "short",
              "label": null,
              "logBase": 1,
              "max": null,
              "min": null,
              "show": true
            }
          ]
        },
        {
          "aliasColors": {},
          "bars": false,
          "dashLength": 10,
          "dashes": false,
          "datasource": null,
          "fill": 1,
          "id": 18,
          "legend": {
            "avg": false,
            "current": false,
            "max": false,
            "min": false,
            "show": true,
            "total": false,
            "values": false
          },
          "lines": true,
          "linewidth": 1,
          "links": [],
          "nullPointMode": "null",
          "percentage": false,
          "pointradius": 5,
          "points": false,
          "renderer": "flot",
          "seriesOverrides": [],
          "spaceLength": 10,
          "span": 4,
          "stack": false,
          "steppedLine": false,
          "targets": [
            {
              "refId": "A",
              "target": "datadealer.datadealer.device-worker.process-message.*_rate"
            },
            {
              "refId": "B",
              "target": "datadealer.datadealer.dealer.devsvcworker.process-message.*_rate"
            }
          ],
          "thresholds": [],
          "timeFrom": null,
          "timeShift": null,
          "title": "Device worker message processing rates",
          "tooltip": {
            "shared": true,
            "sort": 0,
            "value_type": "individual"
          },
          "type": "graph",
          "xaxis": {
            "buckets": null,
            "mode": "time",
            "name": null,
            "show": true,
            "values": []
          },
          "yaxes": [
            {
              "format": "hertz",
              "label": null,
              "logBase": 1,
              "max": null,
              "min": null,
              "show": true
            },
            {
              "format": "short",
              "label": null,
              "logBase": 1,
              "max": null,
              "min": null,
              "show": true
            }
          ]
        },
        {
          "aliasColors": {},
          "bars": false,
          "dashLength": 10,
          "dashes": false,
          "datasource": null,
          "fill": 1,
          "id": 20,
          "legend": {
            "avg": false,
            "current": false,
            "max": false,
            "min": false,
            "show": true,
            "total": false,
            "values": false
          },
          "lines": true,
          "linewidth": 1,
          "links": [],
          "nullPointMode": "null",
          "percentage": false,
          "pointradius": 5,
          "points": false,
          "renderer": "flot",
          "seriesOverrides": [],
          "spaceLength": 10,
          "span": 4,
          "stack": false,
          "steppedLine": false,
          "targets": [
            {
              "refId": "A",
              "target": "datadealer.datadealer.device-worker.messages-queued-for-processing.count"
            },
            {
              "refId": "B",
              "target": "datadealer.datadealer.dealer.devsvcworker.messages-queued-for-processing.count"
            }
          ],
          "thresholds": [],
          "timeFrom": null,
          "timeShift": null,
          "title": "Node messages pending DD processing",
          "tooltip": {
            "shared": true,
            "sort": 0,
            "value_type": "individual"
          },
          "type": "graph",
          "xaxis": {
            "buckets": null,
            "mode": "time",
            "name": null,
            "show": true,
            "values": []
          },
          "yaxes": [
            {
              "format": "short",
              "label": null,
              "logBase": 1,
              "max": null,
              "min": null,
              "show": true
            },
            {
              "format": "short",
              "label": null,
              "logBase": 1,
              "max": null,
              "min": null,
              "show": true
            }
          ]
        }
      ],
      "repeat": null,
      "repeatIteration": null,
      "repeatRowId": null,
      "showTitle": false,
      "title": "Worker backlog details",
      "titleSize": "h6"
    },
    {
      "collapse": false,
      "height": 250,
      "panels": [
        {
          "aliasColors": {},
          "bars": false,
          "dashLength": 10,
          "dashes": false,
          "datasource": null,
          "fill": 1,
          "id": 28,
          "legend": {
            "avg": false,
            "current": false,
            "max": false,
            "min": false,
            "show": true,
            "total": false,
            "values": false
          },
          "lines": true,
          "linewidth": 1,
          "links": [],
          "nullPointMode": "null",
          "percentage": false,
          "pointradius": 5,
          "points": false,
          "renderer": "flot",
          "seriesOverrides": [],
          "spaceLength": 10,
          "span": 6,
          "stack": false,
          "steppedLine": false,
          "targets": [
            {
              "refId": "A",
              "target": "datadealer.datadealer.device-worker.zmq-dequeue.m1_rate"
            },
            {
              "refId": "B",
              "target": "datadealer.datadealer.device-worker.process-message.m1_rate"
            },
            {
              "refId": "C",
              "target": "datadealer.datadealer.dealer.devsvcworker.zmq-dequeue.m1_rate"
            },
            {
              "refId": "D",
              "target": "datadealer.datadealer.dealer.devsvcworker.process-message.m1_rate"
            }
          ],
          "thresholds": [],
          "timeFrom": null,
          "timeShift": null,
          "title": "LB message incoming vs processed, 1 minute window",
          "tooltip": {
            "shared": true,
            "sort": 0,
            "value_type": "individual"
          },
          "type": "graph",
          "xaxis": {
            "buckets": null,
            "mode": "time",
            "name": null,
            "show": true,
            "values": []
          },
          "yaxes": [
            {
              "format": "hertz",
              "label": null,
              "logBase": 1,
              "max": null,
              "min": null,
              "show": true
            },
            {
              "format": "short",
              "label": null,
              "logBase": 1,
              "max": null,
              "min": null,
              "show": true
            }
          ]
        },
        {
          "aliasColors": {},
          "bars": false,
          "dashLength": 10,
          "dashes": false,
          "datasource": null,
          "fill": 1,
          "id": 29,
          "legend": {
            "avg": false,
            "current": false,
            "max": false,
            "min": false,
            "show": true,
            "total": false,
            "values": false
          },
          "lines": true,
          "linewidth": 1,
          "links": [],
          "nullPointMode": "null",
          "percentage": false,
          "pointradius": 5,
          "points": false,
          "renderer": "flot",
          "seriesOverrides": [],
          "spaceLength": 10,
          "span": 6,
          "stack": false,
          "steppedLine": false,
          "targets": [
            {
              "refId": "A",
              "target": "datadealer.datadealer.device-worker.messages-queued-for-processing.count"
            },
            {
              "refId": "B",
              "target": "datadealer.datadealer.dealer.devsvcworker.messages-queued-for-processing.count"
            }
          ],
          "thresholds": [],
          "timeFrom": null,
          "timeShift": null,
          "title": "Device message backlog",
          "tooltip": {
            "shared": true,
            "sort": 0,
            "value_type": "individual"
          },
          "type": "graph",
          "xaxis": {
            "buckets": null,
            "mode": "time",
            "name": null,
            "show": true,
            "values": []
          },
          "yaxes": [
            {
              "format": "short",
              "label": null,
              "logBase": 1,
              "max": null,
              "min": null,
              "show": true
            },
            {
              "format": "short",
              "label": null,
              "logBase": 1,
              "max": null,
              "min": null,
              "show": true
            }
          ]
        }
      ],
      "repeat": null,
      "repeatIteration": null,
      "repeatRowId": null,
      "showTitle": false,
      "title": "worker backlog info",
      "titleSize": "h6"
    },
    {
      "collapse": false,
      "height": 250,
      "panels": [
        {
          "aliasColors": {},
          "bars": false,
          "dashLength": 10,
          "dashes": false,
          "datasource": null,
          "fill": 1,
          "id": 21,
          "legend": {
            "avg": false,
            "current": false,
            "max": false,
            "min": false,
            "show": true,
            "total": false,
            "values": false
          },
          "lines": true,
          "linewidth": 1,
          "links": [],
          "nullPointMode": "null",
          "percentage": false,
          "pointradius": 5,
          "points": false,
          "renderer": "flot",
          "seriesOverrides": [],
          "spaceLength": 10,
          "span": 6,
          "stack": false,
          "steppedLine": false,
          "targets": [
            {
              "refId": "A",
              "target": "datadealer.datadealer.device-worker.resolve-node.*_rate"
            },
            {
              "refId": "B",
              "target": "datadealer.datadealer.device-worker.resolve-video-node.*_rate"
            },
            {
              "refId": "C",
              "target": "datadealer.datadealer.device-worker.clear-alerts.*_rate"
            },
            {
              "refId": "D",
              "target": "datadealer.datadealer.device-worker.upsert-alert.*_rate"
            },
            {
              "refId": "E",
              "target": "datadealer.datadealer.dealer.devsvcworker.resolve-node.*_rate"
            },
            {
              "refId": "F",
              "target": "datadealer.datadealer.dealer.devsvcworker.resolve-video-node.*_rate"
            },
            {
              "refId": "G",
              "target": "datadealer.datadealer.dealer.devsvcworker.clear-alerts.*_rate"
            },
            {
              "refId": "H",
              "target": "datadealer.datadealer.dealer.devsvcworker.upsert-alert.*_rate"
            }
          ],
          "thresholds": [],
          "timeFrom": null,
          "timeShift": null,
          "title": "Device worker Neo4j query rates",
          "tooltip": {
            "shared": true,
            "sort": 0,
            "value_type": "individual"
          },
          "type": "graph",
          "xaxis": {
            "buckets": null,
            "mode": "time",
            "name": null,
            "show": true,
            "values": []
          },
          "yaxes": [
            {
              "format": "hertz",
              "label": null,
              "logBase": 1,
              "max": null,
              "min": null,
              "show": true
            },
            {
              "format": "short",
              "label": null,
              "logBase": 1,
              "max": null,
              "min": null,
              "show": true
            }
          ]
        },
        {
          "aliasColors": {},
          "bars": false,
          "dashLength": 10,
          "dashes": false,
          "datasource": null,
          "fill": 1,
          "id": 22,
          "legend": {
            "avg": false,
            "current": false,
            "max": false,
            "min": false,
            "show": true,
            "total": false,
            "values": false
          },
          "lines": true,
          "linewidth": 1,
          "links": [],
          "nullPointMode": "null",
          "percentage": false,
          "pointradius": 5,
          "points": false,
          "renderer": "flot",
          "seriesOverrides": [],
          "spaceLength": 10,
          "span": 6,
          "stack": false,
          "steppedLine": false,
          "targets": [
            {
              "hide": true,
              "refId": "A",
              "target": "datadealer.datadealer.device-worker.resolve-node.p*"
            },
            {
              "hide": true,
              "refId": "B",
              "target": "datadealer.datadealer.device-worker.resolve-video-node.p*"
            },
            {
              "hide": true,
              "refId": "C",
              "target": "datadealer.datadealer.device-worker.clear-alerts.p*"
            },
            {
              "hide": true,
              "refId": "D",
              "target": "datadealer.datadealer.device-worker.upsert-alert.p*"
            },
            {
              "refId": "E",
              "target": "datadealer.datadealer.dealer.devsvcworker.resolve-node.p*"
            },
            {
              "refId": "F",
              "target": "datadealer.datadealer.dealer.devsvcworker.resolve-video-node.p*"
            },
            {
              "refId": "G",
              "target": "datadealer.datadealer.dealer.devsvcworker.clear-alerts.p*"
            },
            {
              "refId": "H",
              "target": "datadealer.datadealer.dealer.devsvcworker.upsert-alert.p*"
            }
          ],
          "thresholds": [],
          "timeFrom": null,
          "timeShift": null,
          "title": "Device worker Neo4j query percentiles",
          "tooltip": {
            "shared": true,
            "sort": 0,
            "value_type": "individual"
          },
          "type": "graph",
          "xaxis": {
            "buckets": null,
            "mode": "time",
            "name": null,
            "show": true,
            "values": []
          },
          "yaxes": [
            {
              "format": "dtdurationms",
              "label": null,
              "logBase": 1,
              "max": null,
              "min": null,
              "show": true
            },
            {
              "format": "short",
              "label": null,
              "logBase": 1,
              "max": null,
              "min": null,
              "show": true
            }
          ]
        }
      ],
      "repeat": null,
      "repeatIteration": null,
      "repeatRowId": null,
      "showTitle": false,
      "title": "worker initial Neo4j",
      "titleSize": "h6"
    },
    {
      "collapse": false,
      "height": 250,
      "panels": [
        {
          "aliasColors": {},
          "bars": false,
          "dashLength": 10,
          "dashes": false,
          "datasource": null,
          "fill": 1,
          "id": 13,
          "legend": {
            "avg": false,
            "current": false,
            "hideEmpty": true,
            "max": false,
            "min": false,
            "show": true,
            "total": false,
            "values": false
          },
          "lines": true,
          "linewidth": 1,
          "links": [],
          "nullPointMode": "null",
          "percentage": false,
          "pointradius": 5,
          "points": false,
          "renderer": "flot",
          "seriesOverrides": [],
          "spaceLength": 10,
          "span": 6,
          "stack": false,
          "steppedLine": false,
          "targets": [
            {
              "hide": false,
              "refId": "A",
              "target": "*.datadealer.device-service-worker.m1_rate"
            },
            {
              "refId": "B",
              "target": "*.datadealer.device-service-worker.*.m1_rate"
            },
            {
              "refId": "C",
              "target": "*.datadealer.dealer.devsvcworker.process-message.m1_rate"
            },
            {
              "refId": "D",
              "target": "*.datadealer.dealer.devsvcworker.device-service-worker.*.m1_rate"
            }
          ],
          "thresholds": [],
          "timeFrom": null,
          "timeShift": null,
          "title": "LB message processing, 1 minute window",
          "tooltip": {
            "shared": true,
            "sort": 0,
            "value_type": "individual"
          },
          "type": "graph",
          "xaxis": {
            "buckets": null,
            "mode": "time",
            "name": null,
            "show": true,
            "values": []
          },
          "yaxes": [
            {
              "format": "hertz",
              "label": null,
              "logBase": 1,
              "max": null,
              "min": null,
              "show": true
            },
            {
              "format": "short",
              "label": null,
              "logBase": 1,
              "max": null,
              "min": null,
              "show": true
            }
          ]
        },
        {
          "aliasColors": {},
          "bars": false,
          "dashLength": 10,
          "dashes": false,
          "datasource": null,
          "fill": 1,
          "id": 14,
          "legend": {
            "avg": false,
            "current": false,
            "hideEmpty": true,
            "hideZero": false,
            "max": false,
            "min": false,
            "show": true,
            "total": false,
            "values": false
          },
          "lines": true,
          "linewidth": 1,
          "links": [],
          "nullPointMode": "null",
          "percentage": false,
          "pointradius": 5,
          "points": false,
          "renderer": "flot",
          "seriesOverrides": [],
          "spaceLength": 10,
          "span": 6,
          "stack": false,
          "steppedLine": false,
          "targets": [
            {
              "refId": "A",
              "target": "*.datadealer.device-service-worker.p999"
            },
            {
              "refId": "B",
              "target": "*.datadealer.device-service-worker.*.p999"
            },
            {
              "refId": "C",
              "target": "*.datadealer.dealer.devsvcworker.device-service-worker.p999"
            },
            {
              "refId": "D",
              "target": "*.datadealer.dealer.devsvcworker.device-service-worker.*.p999"
            }
          ],
          "thresholds": [],
          "timeFrom": null,
          "timeShift": null,
          "title": "LB worker 99.9 percentiles",
          "tooltip": {
            "shared": true,
            "sort": 0,
            "value_type": "individual"
          },
          "type": "graph",
          "xaxis": {
            "buckets": null,
            "mode": "time",
            "name": null,
            "show": true,
            "values": []
          },
          "yaxes": [
            {
              "format": "dtdurationms",
              "label": null,
              "logBase": 1,
              "max": null,
              "min": null,
              "show": true
            },
            {
              "format": "short",
              "label": null,
              "logBase": 1,
              "max": null,
              "min": null,
              "show": true
            }
          ]
        }
      ],
      "repeat": null,
      "repeatIteration": null,
      "repeatRowId": null,
      "showTitle": false,
      "title": "DD worker details",
      "titleSize": "h6"
    },
    {
      "collapse": false,
      "height": 250,
      "panels": [
        {
          "aliasColors": {},
          "bars": false,
          "dashLength": 10,
          "dashes": false,
          "datasource": null,
          "fill": 1,
          "id": 6,
          "legend": {
            "avg": false,
            "current": false,
            "max": false,
            "min": false,
            "show": true,
            "total": false,
            "values": false
          },
          "lines": true,
          "linewidth": 1,
          "links": [],
          "nullPointMode": "null",
          "percentage": false,
          "pointradius": 5,
          "points": false,
          "renderer": "flot",
          "seriesOverrides": [],
          "spaceLength": 10,
          "span": 6,
          "stack": false,
          "steppedLine": false,
          "targets": [
            {
              "refId": "B",
              "target": "*.datadealer.device-service-worker.m*_*"
            },
            {
              "refId": "C",
              "target": "datadealer.datadealer.dealer.devsvcworker.device-service-worker.m*_rate"
            }
          ],
          "thresholds": [],
          "timeFrom": null,
          "timeShift": null,
          "title": "DD consumption rates",
          "tooltip": {
            "shared": true,
            "sort": 0,
            "value_type": "individual"
          },
          "type": "graph",
          "xaxis": {
            "buckets": null,
            "mode": "time",
            "name": null,
            "show": true,
            "values": []
          },
          "yaxes": [
            {
              "format": "hertz",
              "label": null,
              "logBase": 1,
              "max": null,
              "min": null,
              "show": true
            },
            {
              "format": "short",
              "label": null,
              "logBase": 1,
              "max": null,
              "min": null,
              "show": true
            }
          ]
        },
        {
          "aliasColors": {},
          "bars": false,
          "dashLength": 10,
          "dashes": false,
          "datasource": null,
          "fill": 1,
          "id": 7,
          "legend": {
            "avg": false,
            "current": false,
            "max": false,
            "min": false,
            "show": true,
            "total": false,
            "values": false
          },
          "lines": true,
          "linewidth": 1,
          "links": [],
          "nullPointMode": "null",
          "percentage": false,
          "pointradius": 5,
          "points": false,
          "renderer": "flot",
          "seriesOverrides": [],
          "spaceLength": 10,
          "span": 6,
          "stack": false,
          "steppedLine": false,
          "targets": [
            {
              "refId": "A",
              "target": "default.default.device-service-worker.p*"
            },
            {
              "refId": "C",
              "target": "datadealer.datadealer.dealer.devsvcworker.device-service-worker.p*"
            }
          ],
          "thresholds": [],
          "timeFrom": null,
          "timeShift": null,
          "title": "Time to service LB msg",
          "tooltip": {
            "shared": true,
            "sort": 0,
            "value_type": "individual"
          },
          "type": "graph",
          "xaxis": {
            "buckets": null,
            "mode": "time",
            "name": null,
            "show": true,
            "values": []
          },
          "yaxes": [
            {
              "format": "dtdurationms",
              "label": null,
              "logBase": 1,
              "max": null,
              "min": null,
              "show": true
            },
            {
              "format": "short",
              "label": null,
              "logBase": 1,
              "max": null,
              "min": null,
              "show": true
            }
          ]
        }
      ],
      "repeat": null,
      "repeatIteration": null,
      "repeatRowId": null,
      "showTitle": false,
      "title": "DD worker info",
      "titleSize": "h6"
    },
    {
      "collapse": false,
      "height": 250,
      "panels": [
        {
          "aliasColors": {},
          "bars": false,
          "dashLength": 10,
          "dashes": false,
          "datasource": null,
          "fill": 1,
          "id": 30,
          "legend": {
            "avg": false,
            "current": false,
            "max": false,
            "min": false,
            "show": true,
            "total": false,
            "values": false
          },
          "lines": true,
          "linewidth": 1,
          "links": [],
          "nullPointMode": "null",
          "percentage": false,
          "pointradius": 5,
          "points": false,
          "renderer": "flot",
          "seriesOverrides": [],
          "spaceLength": 10,
          "span": 6,
          "stack": false,
          "steppedLine": false,
          "targets": [
            {
              "refId": "A",
              "target": "datadealer.datadealer.dealer.devsvcctrl.device-service-control.*.m1_rate"
            },
            {
              "refId": "B",
              "target": "datadealer.datadealer.dealer.devsvcctrl.device-service-control.m1_rate"
            }
          ],
          "thresholds": [],
          "timeFrom": null,
          "timeShift": null,
          "title": "LB Control rates, 1 minute window",
          "tooltip": {
            "shared": true,
            "sort": 0,
            "value_type": "individual"
          },
          "type": "graph",
          "xaxis": {
            "buckets": null,
            "mode": "time",
            "name": null,
            "show": true,
            "values": []
          },
          "yaxes": [
            {
              "format": "hertz",
              "label": null,
              "logBase": 1,
              "max": null,
              "min": null,
              "show": true
            },
            {
              "format": "short",
              "label": null,
              "logBase": 1,
              "max": null,
              "min": null,
              "show": true
            }
          ]
        },
        {
          "aliasColors": {},
          "bars": false,
          "dashLength": 10,
          "dashes": false,
          "datasource": null,
          "fill": 1,
          "id": 31,
          "legend": {
            "avg": false,
            "current": false,
            "max": false,
            "min": false,
            "show": true,
            "total": false,
            "values": false
          },
          "lines": true,
          "linewidth": 1,
          "links": [],
          "nullPointMode": "null",
          "percentage": false,
          "pointradius": 5,
          "points": false,
          "renderer": "flot",
          "seriesOverrides": [],
          "spaceLength": 10,
          "span": 6,
          "stack": false,
          "steppedLine": false,
          "targets": [
            {
              "refId": "A",
              "target": "datadealer.datadealer.dealer.devsvcctrl.device-service-control.*.p999"
            },
            {
              "refId": "B",
              "target": "datadealer.datadealer.dealer.devsvcctrl.device-service-control.p999"
            }
          ],
          "thresholds": [],
          "timeFrom": null,
          "timeShift": null,
          "title": "LB Worker percentiles",
          "tooltip": {
            "shared": true,
            "sort": 0,
            "value_type": "individual"
          },
          "type": "graph",
          "xaxis": {
            "buckets": null,
            "mode": "time",
            "name": null,
            "show": true,
            "values": []
          },
          "yaxes": [
            {
              "format": "dtdurationms",
              "label": null,
              "logBase": 1,
              "max": null,
              "min": null,
              "show": true
            },
            {
              "format": "short",
              "label": null,
              "logBase": 1,
              "max": null,
              "min": null,
              "show": true
            }
          ]
        }
      ],
      "repeat": null,
      "repeatIteration": null,
      "repeatRowId": null,
      "showTitle": false,
      "title": "DD control details",
      "titleSize": "h6"
    },
    {
      "collapse": false,
      "height": 250,
      "panels": [
        {
          "aliasColors": {},
          "bars": false,
          "dashLength": 10,
          "dashes": false,
          "datasource": null,
          "fill": 1,
          "id": 23,
          "legend": {
            "avg": false,
            "current": false,
            "max": false,
            "min": false,
            "show": true,
            "total": false,
            "values": false
          },
          "lines": true,
          "linewidth": 1,
          "links": [],
          "nullPointMode": "null",
          "percentage": false,
          "pointradius": 5,
          "points": false,
          "renderer": "flot",
          "seriesOverrides": [],
          "spaceLength": 10,
          "span": 6,
          "stack": false,
          "steppedLine": false,
          "targets": [
            {
              "refId": "A",
              "target": "datadealer.datadealer.utils.cape.casel-timer.m1_rate"
            },
            {
              "refId": "B",
              "target": "datadealer.datadealer.utils.cape.casel-timer.*.m1_rate"
            }
          ],
          "thresholds": [],
          "timeFrom": null,
          "timeShift": null,
          "title": "Cape APIs: 1-minute rate",
          "tooltip": {
            "shared": true,
            "sort": 0,
            "value_type": "individual"
          },
          "type": "graph",
          "xaxis": {
            "buckets": null,
            "mode": "time",
            "name": null,
            "show": true,
            "values": []
          },
          "yaxes": [
            {
              "format": "hertz",
              "label": null,
              "logBase": 1,
              "max": null,
              "min": null,
              "show": true
            },
            {
              "format": "short",
              "label": null,
              "logBase": 1,
              "max": null,
              "min": null,
              "show": true
            }
          ]
        },
        {
          "aliasColors": {},
          "bars": false,
          "dashLength": 10,
          "dashes": false,
          "datasource": null,
          "fill": 1,
          "id": 24,
          "legend": {
            "avg": false,
            "current": false,
            "max": false,
            "min": false,
            "show": true,
            "total": false,
            "values": false
          },
          "lines": true,
          "linewidth": 1,
          "links": [],
          "nullPointMode": "null",
          "percentage": false,
          "pointradius": 5,
          "points": false,
          "renderer": "flot",
          "seriesOverrides": [],
          "spaceLength": 10,
          "span": 6,
          "stack": false,
          "steppedLine": false,
          "targets": [
            {
              "refId": "A",
              "target": "datadealer.datadealer.utils.cape.casel-timer.p999"
            },
            {
              "refId": "B",
              "target": "datadealer.datadealer.utils.cape.casel-timer.*.p999"
            }
          ],
          "thresholds": [],
          "timeFrom": null,
          "timeShift": null,
          "title": "Cape APIs: 99.9 percentile",
          "tooltip": {
            "shared": true,
            "sort": 0,
            "value_type": "individual"
          },
          "type": "graph",
          "xaxis": {
            "buckets": null,
            "mode": "time",
            "name": null,
            "show": true,
            "values": []
          },
          "yaxes": [
            {
              "format": "dtdurationms",
              "label": null,
              "logBase": 1,
              "max": null,
              "min": null,
              "show": true
            },
            {
              "format": "short",
              "label": null,
              "logBase": 1,
              "max": null,
              "min": null,
              "show": true
            }
          ]
        }
      ],
      "repeat": null,
      "repeatIteration": null,
      "repeatRowId": null,
      "showTitle": false,
      "title": "Cape timer details",
      "titleSize": "h6"
    },
    {
      "collapse": false,
      "height": 250,
      "panels": [
        {
          "aliasColors": {},
          "bars": false,
          "dashLength": 10,
          "dashes": false,
          "datasource": null,
          "fill": 1,
          "id": 26,
          "legend": {
            "avg": false,
            "current": false,
            "max": false,
            "min": false,
            "show": true,
            "total": false,
            "values": false
          },
          "lines": true,
          "linewidth": 1,
          "links": [],
          "nullPointMode": "null",
          "percentage": false,
          "pointradius": 5,
          "points": false,
          "renderer": "flot",
          "seriesOverrides": [],
          "spaceLength": 10,
          "span": 6,
          "stack": false,
          "steppedLine": false,
          "targets": [
            {
              "refId": "A",
              "target": "datadealer.datadealer.neo4j-timer.*_rate"
            }
          ],
          "thresholds": [],
          "timeFrom": null,
          "timeShift": null,
          "title": "Neo4j rates",
          "tooltip": {
            "shared": true,
            "sort": 0,
            "value_type": "individual"
          },
          "type": "graph",
          "xaxis": {
            "buckets": null,
            "mode": "time",
            "name": null,
            "show": true,
            "values": []
          },
          "yaxes": [
            {
              "format": "hertz",
              "label": null,
              "logBase": 1,
              "max": null,
              "min": null,
              "show": true
            },
            {
              "format": "short",
              "label": null,
              "logBase": 1,
              "max": null,
              "min": null,
              "show": true
            }
          ]
        },
        {
          "aliasColors": {},
          "bars": false,
          "dashLength": 10,
          "dashes": false,
          "datasource": null,
          "fill": 1,
          "id": 27,
          "legend": {
            "avg": false,
            "current": false,
            "max": false,
            "min": false,
            "show": true,
            "total": false,
            "values": false
          },
          "lines": true,
          "linewidth": 1,
          "links": [],
          "nullPointMode": "null",
          "percentage": false,
          "pointradius": 5,
          "points": false,
          "renderer": "flot",
          "seriesOverrides": [],
          "spaceLength": 10,
          "span": 6,
          "stack": false,
          "steppedLine": false,
          "targets": [
            {
              "refId": "A",
              "target": "datadealer.datadealer.neo4j-timer.p*"
            }
          ],
          "thresholds": [],
          "timeFrom": null,
          "timeShift": null,
          "title": "Neo4j percentiles",
          "tooltip": {
            "shared": true,
            "sort": 0,
            "value_type": "individual"
          },
          "type": "graph",
          "xaxis": {
            "buckets": null,
            "mode": "time",
            "name": null,
            "show": true,
            "values": []
          },
          "yaxes": [
            {
              "format": "dtdurationms",
              "label": null,
              "logBase": 1,
              "max": null,
              "min": null,
              "show": true
            },
            {
              "format": "short",
              "label": null,
              "logBase": 1,
              "max": null,
              "min": null,
              "show": true
            }
          ]
        }
      ],
      "repeat": null,
      "repeatIteration": null,
      "repeatRowId": null,
      "showTitle": false,
      "title": "Neo4j timer",
      "titleSize": "h6"
    },
    {
      "collapse": false,
      "height": 250,
      "panels": [
        {
          "aliasColors": {},
          "bars": false,
          "dashLength": 10,
          "dashes": false,
          "datasource": null,
          "fill": 1,
          "id": 26,
          "legend": {
            "avg": false,
            "current": false,
            "max": false,
            "min": false,
            "show": true,
            "total": false,
            "values": false
          },
          "lines": true,
          "linewidth": 1,
          "links": [],
          "nullPointMode": "null",
          "percentage": false,
          "pointradius": 5,
          "points": false,
          "renderer": "flot",
          "seriesOverrides": [],
          "spaceLength": 10,
          "span": 6,
          "stack": false,
          "steppedLine": false,
          "targets": [
            {
              "refId": "A",
              "target": "datadealer.datadealer.cassandra-timer.*_rate"
            }
          ],
          "thresholds": [],
          "timeFrom": null,
          "timeShift": null,
          "title": "Cassandra transation rates",
          "tooltip": {
            "shared": true,
            "sort": 0,
            "value_type": "individual"
          },
          "type": "graph",
          "xaxis": {
            "buckets": null,
            "mode": "time",
            "name": null,
            "show": true,
            "values": []
          },
          "yaxes": [
            {
              "format": "hertz",
              "label": null,
              "logBase": 1,
              "max": null,
              "min": null,
              "show": true
            },
            {
              "format": "short",
              "label": null,
              "logBase": 1,
              "max": null,
              "min": null,
              "show": true
            }
          ]
        },
        {
          "aliasColors": {},
          "bars": false,
          "dashLength": 10,
          "dashes": false,
          "datasource": null,
          "fill": 1,
          "id": 27,
          "legend": {
            "avg": false,
            "current": false,
            "max": false,
            "min": false,
            "show": true,
            "total": false,
            "values": false
          },
          "lines": true,
          "linewidth": 1,
          "links": [],
          "nullPointMode": "null",
          "percentage": false,
          "pointradius": 5,
          "points": false,
          "renderer": "flot",
          "seriesOverrides": [],
          "spaceLength": 10,
          "span": 6,
          "stack": false,
          "steppedLine": false,
          "targets": [
            {
              "refId": "A",
              "target": "datadealer.datadealer.cassandra-timer.p*"
            }
          ],
          "thresholds": [],
          "timeFrom": null,
          "timeShift": null,
          "title": "Cassandra transaction percentiles",
          "tooltip": {
            "shared": true,
            "sort": 0,
            "value_type": "individual"
          },
          "type": "graph",
          "xaxis": {
            "buckets": null,
            "mode": "time",
            "name": null,
            "show": true,
            "values": []
          },
          "yaxes": [
            {
              "format": "dtdurationms",
              "label": null,
              "logBase": 1,
              "max": null,
              "min": null,
              "show": true
            },
            {
              "format": "short",
              "label": null,
              "logBase": 1,
              "max": null,
              "min": null,
              "show": true
            }
          ]
        }
      ],
      "repeat": null,
      "repeatIteration": null,
      "repeatRowId": null,
      "showTitle": false,
      "title": "Cassandra transaction timer",
      "titleSize": "h6"
    },
    {
      "collapse": false,
      "height": 250,
      "panels": [
        {
          "aliasColors": {},
          "bars": false,
          "dashLength": 10,
          "dashes": false,
          "datasource": null,
          "fill": 1,
          "id": 11,
          "legend": {
            "avg": false,
            "current": false,
            "max": false,
            "min": false,
            "show": true,
            "total": false,
            "values": false
          },
          "lines": true,
          "linewidth": 1,
          "links": [],
          "nullPointMode": "null",
          "percentage": false,
          "pointradius": 5,
          "points": false,
          "renderer": "flot",
          "seriesOverrides": [],
          "spaceLength": 10,
          "span": 6,
          "stack": false,
          "steppedLine": false,
          "targets": [
            {
              "hide": false,
              "refId": "A",
              "target": "jvm.memory.total.*"
            },
            {
              "hide": false,
              "refId": "B",
              "target": "*.datadealer.jvm.memory.total.*"
            }
          ],
          "thresholds": [],
          "timeFrom": null,
          "timeShift": null,
          "title": "JVM memory",
          "tooltip": {
            "shared": true,
            "sort": 0,
            "value_type": "individual"
          },
          "type": "graph",
          "xaxis": {
            "buckets": null,
            "mode": "time",
            "name": null,
            "show": true,
            "values": []
          },
          "yaxes": [
            {
              "format": "bytes",
              "label": null,
              "logBase": 1,
              "max": null,
              "min": null,
              "show": true
            },
            {
              "format": "short",
              "label": null,
              "logBase": 1,
              "max": null,
              "min": null,
              "show": true
            }
          ]
        },
        {
          "aliasColors": {},
          "bars": false,
          "dashLength": 10,
          "dashes": false,
          "datasource": null,
          "fill": 1,
          "id": 12,
          "legend": {
            "avg": false,
            "current": false,
            "max": false,
            "min": false,
            "show": true,
            "total": false,
            "values": false
          },
          "lines": true,
          "linewidth": 1,
          "links": [],
          "nullPointMode": "null",
          "percentage": false,
          "pointradius": 5,
          "points": false,
          "renderer": "flot",
          "seriesOverrides": [],
          "spaceLength": 10,
          "span": 6,
          "stack": false,
          "steppedLine": false,
          "targets": [
            {
              "hide": false,
              "refId": "A",
              "target": "jvm.thread.*.count"
            },
            {
              "refId": "B",
              "target": "*.datadealer.jvm.thread.*.count"
            }
          ],
          "thresholds": [],
          "timeFrom": null,
          "timeShift": null,
          "title": "JVM Threads",
          "tooltip": {
            "shared": true,
            "sort": 0,
            "value_type": "individual"
          },
          "type": "graph",
          "xaxis": {
            "buckets": null,
            "mode": "time",
            "name": null,
            "show": true,
            "values": []
          },
          "yaxes": [
            {
              "format": "short",
              "label": null,
              "logBase": 1,
              "max": null,
              "min": null,
              "show": true
            },
            {
              "format": "short",
              "label": null,
              "logBase": 1,
              "max": null,
              "min": null,
              "show": true
            }
          ]
        }
      ],
      "repeat": null,
      "repeatIteration": null,
      "repeatRowId": null,
      "showTitle": false,
      "title": "JVM sys info",
      "titleSize": "h6"
    },
    {
      "collapse": false,
      "height": 250,
      "panels": [
        {
          "aliasColors": {},
          "bars": false,
          "dashLength": 10,
          "dashes": false,
          "datasource": null,
          "fill": 1,
          "id": 8,
          "legend": {
            "avg": false,
            "current": false,
            "max": false,
            "min": false,
            "show": true,
            "total": false,
            "values": false
          },
          "lines": true,
          "linewidth": 1,
          "links": [],
          "nullPointMode": "null",
          "percentage": false,
          "pointradius": 5,
          "points": false,
          "renderer": "flot",
          "seriesOverrides": [],
          "spaceLength": 10,
          "span": 6,
          "stack": false,
          "steppedLine": false,
          "targets": [
            {
              "refId": "A",
              "target": "collectd.*datadealer*.cpu-*.cpu-user"
            }
          ],
          "thresholds": [],
          "timeFrom": null,
          "timeShift": null,
          "title": "DD sys CPU",
          "tooltip": {
            "shared": true,
            "sort": 0,
            "value_type": "individual"
          },
          "type": "graph",
          "xaxis": {
            "buckets": null,
            "mode": "time",
            "name": null,
            "show": true,
            "values": []
          },
          "yaxes": [
            {
              "format": "short",
              "label": null,
              "logBase": 1,
              "max": null,
              "min": null,
              "show": true
            },
            {
              "format": "short",
              "label": null,
              "logBase": 1,
              "max": null,
              "min": null,
              "show": true
            }
          ]
        },
        {
          "aliasColors": {},
          "bars": false,
          "dashLength": 10,
          "dashes": false,
          "datasource": null,
          "fill": 1,
          "id": 9,
          "legend": {
            "avg": false,
            "current": false,
            "max": false,
            "min": false,
            "show": true,
            "total": false,
            "values": false
          },
          "lines": true,
          "linewidth": 1,
          "links": [],
          "nullPointMode": "null",
          "percentage": false,
          "pointradius": 5,
          "points": false,
          "renderer": "flot",
          "seriesOverrides": [],
          "spaceLength": 10,
          "span": 6,
          "stack": false,
          "steppedLine": false,
          "targets": [
            {
              "refId": "A",
              "target": "collectd.*datadealer*.memory.*"
            }
          ],
          "thresholds": [],
          "timeFrom": null,
          "timeShift": null,
          "title": "DD sys memory",
          "tooltip": {
            "shared": true,
            "sort": 0,
            "value_type": "individual"
          },
          "type": "graph",
          "xaxis": {
            "buckets": null,
            "mode": "time",
            "name": null,
            "show": true,
            "values": []
          },
          "yaxes": [
            {
              "format": "short",
              "label": null,
              "logBase": 1,
              "max": null,
              "min": null,
              "show": true
            },
            {
              "format": "short",
              "label": null,
              "logBase": 1,
              "max": null,
              "min": null,
              "show": true
            }
          ]
        }
      ],
      "repeat": null,
      "repeatIteration": null,
      "repeatRowId": null,
      "showTitle": false,
      "title": "DD sys stats",
      "titleSize": "h6"
    },
    {
      "collapse": false,
      "height": 250,
      "panels": [
        {
          "aliasColors": {},
          "bars": false,
          "dashLength": 10,
          "dashes": false,
          "datasource": null,
          "fill": 1,
          "id": 15,
          "legend": {
            "avg": false,
            "current": false,
            "max": false,
            "min": false,
            "show": true,
            "total": false,
            "values": false
          },
          "lines": true,
          "linewidth": 1,
          "links": [],
          "nullPointMode": "null",
          "percentage": false,
          "pointradius": 5,
          "points": false,
          "renderer": "flot",
          "seriesOverrides": [],
          "spaceLength": 10,
          "span": 12,
          "stack": false,
          "steppedLine": false,
          "targets": [
            {
              "refId": "A",
              "target": "collectd.*.df-root.df_complex-free"
            }
          ],
          "thresholds": [],
          "timeFrom": null,
          "timeShift": null,
          "title": "Free disk",
          "tooltip": {
            "shared": true,
            "sort": 0,
            "value_type": "individual"
          },
          "type": "graph",
          "xaxis": {
            "buckets": null,
            "mode": "time",
            "name": null,
            "show": true,
            "values": []
          },
          "yaxes": [
            {
              "format": "bytes",
              "label": null,
              "logBase": 1,
              "max": null,
              "min": null,
              "show": true
            },
            {
              "format": "short",
              "label": null,
              "logBase": 1,
              "max": null,
              "min": null,
              "show": true
            }
          ]
        }
      ],
      "repeat": null,
      "repeatIteration": null,
      "repeatRowId": null,
      "showTitle": false,
      "title": "Free disk",
      "titleSize": "h6"
    }
  ],
  "schemaVersion": 14,
  "style": "dark",
  "tags": [],
  "templating": {
    "list": []
  },
  "time": {
    "from": "now-24h",
    "to": "now"
  },
  "timepicker": {
    "refresh_intervals": [
      "5s",
      "10s",
      "30s",
      "1m",
      "5m",
      "15m",
      "30m",
      "1h",
      "2h",
      "1d"
    ],
    "time_options": [
      "5m",
      "15m",
      "1h",
      "6h",
      "12h",
      "24h",
      "2d",
      "7d",
      "30d"
    ]
  },
  "timezone": "browser",
  "title": "Datadealer",
  "version": 1
}
